.gitattributes
.gitignore
.readthedocs.yaml
LICENSE.txt
MANIFEST.in
README.rst
pyproject.toml
setup.py
.github/workflows/ci.yml
.github/workflows/publish.yml
doc/Makefile
doc/conf.py
doc/index.rst
doc/make.bat
doc/obr101010_comparison.png
doc/obr101010_comparison.pro
doc/qsg.rst
doc/readme.rst
doc/requirements.txt
doc/stis_cti.rst
doc/_templates/layout.html
src/StisFixYCte.c
src/StisPixCteCorr.h
src/StisPixCteCorr_funcs.c
src/StisPixCte_FixY.c
stis_cti/StisPixCteCorr.py
stis_cti/__init__.py
stis_cti/archive_dark_query.py
stis_cti/custom_superdark_info.py
stis_cti/stis_cti.py
stis_cti/test_stis_cti.py
stis_cti.egg-info/PKG-INFO
stis_cti.egg-info/SOURCES.txt
stis_cti.egg-info/dependency_links.txt
stis_cti.egg-info/entry_points.txt
stis_cti.egg-info/requires.txt
stis_cti.egg-info/top_level.txt
stis_cti/data/a01_stis_pcte.fits
stis_cti/data/a02_stis_pcte.fits