Metadata-Version: 2.4
Name: stis_cti
Version: 1.6.2
Summary: Pixel-based CTI-correction for HST/STIS CCD data
Home-page: https://www.stsci.edu/hst/instrumentation/stis/data-analysis-and-software-tools/pixel-based-cti
Author: Sean Lockwood, Phil Hodge, Pey Lian Lim, W.J. Hack, J. Anderson, Matt Davis
Author-email: lockwood@stsci.edu
Maintainer: Sean Lockwood
Maintainer-email: lockwood@stsci.edu
License: BSD-new
Project-URL: Homepage, https://www.stsci.edu/hst/instrumentation/stis/data-analysis-and-software-tools/pixel-based-cti
Project-URL: Documentation, https://stis-cti.readthedocs.io
Project-URL: Help Desk, https://hsthelp.stsci.edu
Project-URL: Source Code, https://github.com/spacetelescope/stis_cti
Project-URL: Issues, https://github.com/spacetelescope/stis_cti/issues
Keywords: astronomy
Classifier: Programming Language :: Python :: 3
Classifier: Programming Language :: C
Classifier: Development Status :: 5 - Production/Stable
Classifier: Operating System :: OS Independent
Classifier: Intended Audience :: Science/Research
Classifier: Topic :: Scientific/Engineering :: Astronomy
Classifier: Topic :: Scientific/Engineering :: Physics
Classifier: Topic :: Software Development :: Libraries :: Python Modules
License-File: LICENSE.txt
Requires-Dist: setuptools
Requires-Dist: numpy
Requires-Dist: astropy>=4.0
Requires-Dist: stistools>=1.2
Requires-Dist: refstis>=0.8.1
Requires-Dist: crds
Requires-Dist: stsci.tools>=3.2.2
Requires-Dist: six
Provides-Extra: docs
Requires-Dist: sphinx; extra == "docs"
Provides-Extra: test
Requires-Dist: pytest; extra == "test"
Dynamic: author
Dynamic: author-email
Dynamic: classifier
Dynamic: description
Dynamic: description-content-type
Dynamic: home-page
Dynamic: keywords
Dynamic: license
Dynamic: license-file
Dynamic: maintainer
Dynamic: maintainer-email
Dynamic: project-url
Dynamic: requires-dist
Dynamic: summary
